vpplib/__init__.py
vpplib/battery_electric_vehicle.py
vpplib/combined_heat_and_power.py
vpplib/component.py
vpplib/electrical_energy_storage.py
vpplib/environment.py
vpplib/heat_pump.py
vpplib/heating_rod.py
vpplib/hydrogen.py
vpplib/operator.py
vpplib/photovoltaic.py
vpplib/thermal_energy_storage.py
vpplib/user_profile.py
vpplib/virtual_power_plant.py
vpplib/wind_power.py
vpplib-0.0.5.dist-info/licenses/LICENSE.txt
vpplib-0.0.5.dist-info/METADATA
vpplib-0.0.5.dist-info/WHEEL
vpplib-0.0.5.dist-info/top_level.txt
vpplib-0.0.5.dist-info/RECORD
