Metadata-Version: 2.4
Name: vpplib
Version: 0.0.5
Summary: simulating distributed energy appliances in a virtual power plant
Author-email: Pyosch <pyosch@posteo.de>
License: GNU General Public License v3 (GPLv3)
Project-URL: GitHub, https://github.com/Pyosch/vpplib
Keywords: virtual power plant,energy system
Classifier: Development Status :: 4 - Beta
Classifier: Programming Language :: Python :: 3.9
Classifier: Programming Language :: Python :: 3.10
Classifier: Programming Language :: Python :: 3.11
Classifier: Programming Language :: Python :: 3.12
Classifier: Programming Language :: Python :: 3.13
Classifier: License :: OSI Approved :: GNU General Public License v3 (GPLv3)
Classifier: Operating System :: OS Independent
Requires-Python: >=3.9
License-File: LICENSE.txt
Requires-Dist: windpowerlib
Requires-Dist: pvlib
Requires-Dist: pandas
Requires-Dist: numpy
Requires-Dist: pandapower
Requires-Dist: simbench
Requires-Dist: simses
Requires-Dist: tqdm
Requires-Dist: matplotlib
Requires-Dist: NREL-PySAM
Requires-Dist: polars
Requires-Dist: numba
Requires-Dist: wetterdienst==0.89.0
Requires-Dist: marshmallow==3.20.1
Dynamic: license-file
